package_manifest/VERSION
package_manifest/__init__.py
package_manifest/_default_values.py
package_manifest/_path.py
package_manifest/_schema.py
package_manifest/_version.py
package_manifest/py.typed
package_manifest-1.0.0.post7.dist-info/LICENSE
package_manifest-1.0.0.post7.dist-info/WHEEL
package_manifest-1.0.0.post7.dist-info/METADATA
package_manifest-1.0.0.post7.dist-info/RECORD
