Metadata-Version: 2.1
Name: package_manifest
Version: 1.0.0.post7
Summary: A YAML based file package manifest framework for defining packages.
Home-page: https://gitlab.com/ci-cd-devops/package-manifest
Author: Russell Smiley
Author-email: im.russell.smiley@gmail.com
Requires-Python: >=3.8
Classifier: License :: OSI Approved :: MIT License
Requires-Dist: aiofiles == 0.7.0
Requires-Dist: pydantic == 1.8.2
Requires-Dist: ruamel.yaml == 0.17.10
Requires-Dist: pygments == 2.7.1
Requires-Dist: build_harness == 0.1.1 ; extra == "dev"
Requires-Dist: sphinx == 4.1.2 ; extra == "doc"
Requires-Dist: sphinx_rtd_theme == 0.5.2 ; extra == "doc"
Requires-Dist: pytest == 6.2.4 ; extra == "test"
Requires-Dist: pytest-asyncio == 0.15.1 ; extra == "test"
Requires-Dist: pytest-cov == 2.12.1 ; extra == "test"
Requires-Dist: pytest-mock == 3.6.1 ; extra == "test"
Provides-Extra: dev
Provides-Extra: doc
Provides-Extra: test
